{
  "animateLoading": false,
  "backgroundColor": "#ffffff",
  "borderColor": "#f4f4f5",
  "borderRadius": "{{appsmith.theme.borderRadius.appBorderRadius}}",
  "borderWidth": "1",
  "bottomRow": 89,
  "bottomRowBeforeCollapse": 85,
  "boxShadow": "{{appsmith.theme.boxShadow.appBoxShadow}}",
  "children": [
    {
      "borderRadius": "{{appsmith.theme.borderRadius.appBorderRadius}}",
      "bottomRow": 1070,
      "boxShadow": "{{appsmith.theme.boxShadow.appBoxShadow}}",
      "canExtend": false,
      "containerStyle": "none",
      "detachFromLayout": true,
      "displayName": "Canvas",
      "dynamicBindingPathList": [
        {
          "key": "borderRadius"
        },
        {
          "key": "boxShadow"
        }
      ],
      "dynamicHeight": "AUTO_HEIGHT",
      "flexLayers": [],
      "hideCard": true,
      "isDeprecated": false,
      "isLoading": false,
      "isVisible": true,
      "key": "qxff5r3ehj",
      "leftColumn": 0,
      "maxDynamicHeight": 9000,
      "minDynamicHeight": 4,
      "minHeight": 100,
      "minWidth": 450,
      "mobileBottomRow": 100,
      "mobileLeftColumn": 0,
      "mobileRightColumn": 356.140625,
      "mobileTopRow": 0,
      "needsErrorInfo": false,
      "onCanvasUI": {
        "disableParentSelection": true,
        "focusBGCSSVar": "--on-canvas-ui-widget-focus",
        "focusColorCSSVar": "--on-canvas-ui-widget-selection",
        "selectionBGCSSVar": "--on-canvas-ui-widget-selection",
        "selectionColorCSSVar": "--on-canvas-ui-widget-focus"
      },
      "parentColumnSpace": 1,
      "parentId": "ozkpjlehdx",
      "parentRowSpace": 1,
      "renderMode": "CANVAS",
      "responsiveBehavior": "fill",
      "rightColumn": 356.140625,
      "topRow": 0,
      "type": "CANVAS_WIDGET",
      "version": 1,
      "widgetId": "rsz6v11wwn",
      "widgetName": "Canvas3"
    }
  ],
  "containerStyle": "card",
  "displayName": "Container",
  "dynamicBindingPathList": [
    {
      "key": "borderRadius"
    },
    {
      "key": "boxShadow"
    },
    {
      "key": "isVisible"
    }
  ],
  "dynamicHeight": "FIXED",
  "dynamicPropertyPathList": [
    {
      "key": "isVisible"
    }
  ],
  "dynamicTriggerPathList": [],
  "flexVerticalAlignment": "stretch",
  "hideCard": false,
  "iconSVG": "/static/media/icon.dcc052e58db911c4c8955c200f4bcf5c.svg",
  "isCanvas": true,
  "isDeprecated": false,
  "isLoading": false,
  "isVisible": "{{!!data_table_all.selectedRow.id}}",
  "key": "0thetie3ej",
  "leftColumn": 44,
  "maxDynamicHeight": 9000,
  "minDynamicHeight": 10,
  "minWidth": 450,
  "mobileBottomRow": 31,
  "mobileLeftColumn": 41,
  "mobileRightColumn": 64,
  "mobileTopRow": 21,
  "needsErrorInfo": false,
  "onCanvasUI": {
    "disableParentSelection": false,
    "focusBGCSSVar": "--on-canvas-ui-widget-focus",
    "focusColorCSSVar": "--on-canvas-ui-widget-selection",
    "selectionBGCSSVar": "--on-canvas-ui-widget-selection",
    "selectionColorCSSVar": "--on-canvas-ui-widget-focus"
  },
  "originalBottomRow": 89,
  "originalTopRow": 25,
  "parentColumnSpace": 15.484375,
  "parentId": "0",
  "parentRowSpace": 10,
  "renderMode": "CANVAS",
  "responsiveBehavior": "fill",
  "rightColumn": 64,
  "searchTags": [
    "div",
    "parent",
    "group"
  ],
  "shouldScrollContents": true,
  "tags": [
    "Layout"
  ],
  "thumbnailSVG": "/static/media/thumbnail.6cb355b93146b5347bbb048a568ed446.svg",
  "topRow": 25,
  "topRowBeforeCollapse": 21,
  "type": "CONTAINER_WIDGET",
  "version": 1,
  "widgetId": "ozkpjlehdx",
  "widgetName": "Container1"
}