{
  "gitSyncId": "6707fe156111781a50ee61bb_23655ddb-ae7f-484e-adfc-6a8b3d34371b",
  "id": "Support Stats_ResolutionChart.getCommonNormalChart",
  "pluginId": "js-plugin",
  "pluginType": "JS",
  "unpublishedAction": {
    "actionConfiguration": {
      "encodeParamsToggle": true,
      "jsArguments": [
        {
          "name": "bg"
        },
        {
          "name": "c"
        }
      ],
      "paginationType": "NONE",
      "timeoutInMillisecond": 10000
    },
    "collectionId": "Support Stats_ResolutionChart",
    "confirmBeforeExecute": false,
    "datasource": {
      "isAutoGenerated": false,
      "name": "UNUSED_DATASOURCE",
      "pluginId": "js-plugin"
    },
    "dynamicBindingPathList": [
      {
        "key": "body"
      }
    ],
    "fullyQualifiedName": "ResolutionChart.getCommonNormalChart",
    "name": "getCommonNormalChart",
    "pageId": "Support Stats",
    "runBehaviour": "MANUAL",
    "userSetOnLoad": false
  }
}