{
  "gitSyncId": "66878fc8470ac81ae3da028e_907b2002-fd19-4e89-b234-d49f4c3caee3",
  "id": "Analytics_MetricsAll.in_getHighResolvedCount",
  "pluginId": "js-plugin",
  "pluginType": "JS",
  "unpublishedAction": {
    "actionConfiguration": {
      "encodeParamsToggle": true,
      "jsArguments": [],
      "paginationType": "NONE",
      "timeoutInMillisecond": 10000
    },
    "collectionId": "Analytics_MetricsAll",
    "confirmBeforeExecute": false,
    "datasource": {
      "isAutoGenerated": false,
      "name": "UNUSED_DATASOURCE",
      "pluginId": "js-plugin"
    },
    "dynamicBindingPathList": [
      {
        "key": "body"
      }
    ],
    "fullyQualifiedName": "MetricsAll.in_getHighResolvedCount",
    "name": "in_getHighResolvedCount",
    "pageId": "Analytics",
    "runBehaviour": "MANUAL",
    "userSetOnLoad": false
  }
}