{
  "gitSyncId": "6733c2c2c9972364a137203c_14aad945-258f-48d9-9832-22b0705ea44c",
  "id": "Unassigned Tickets_FeatureTagUtils.getFeatureTagOptions",
  "pluginId": "js-plugin",
  "pluginType": "JS",
  "unpublishedAction": {
    "actionConfiguration": {
      "encodeParamsToggle": true,
      "jsArguments": [],
      "paginationType": "NONE",
      "timeoutInMillisecond": 10000
    },
    "collectionId": "Unassigned Tickets_FeatureTagUtils",
    "confirmBeforeExecute": false,
    "datasource": {
      "isAutoGenerated": false,
      "name": "UNUSED_DATASOURCE",
      "pluginId": "js-plugin"
    },
    "dynamicBindingPathList": [
      {
        "key": "body"
      }
    ],
    "fullyQualifiedName": "FeatureTagUtils.getFeatureTagOptions",
    "name": "getFeatureTagOptions",
    "pageId": "Unassigned Tickets",
    "runBehaviour": "MANUAL",
    "userSetOnLoad": false
  }
}