{
  "gitSyncId": "66878fc8470ac81ae3da028e_887076ed-fe3c-406f-b555-88cb666e1d62",
  "id": "Analytics_MetricsAll.getCriticalAforceCount",
  "pluginId": "js-plugin",
  "pluginType": "JS",
  "unpublishedAction": {
    "actionConfiguration": {
      "encodeParamsToggle": true,
      "jsArguments": [],
      "paginationType": "NONE",
      "timeoutInMillisecond": 10000
    },
    "collectionId": "Analytics_MetricsAll",
    "confirmBeforeExecute": false,
    "datasource": {
      "isAutoGenerated": false,
      "name": "UNUSED_DATASOURCE",
      "pluginId": "js-plugin"
    },
    "dynamicBindingPathList": [
      {
        "key": "body"
      }
    ],
    "fullyQualifiedName": "MetricsAll.getCriticalAforceCount",
    "name": "getCriticalAforceCount",
    "pageId": "Analytics",
    "runBehaviour": "MANUAL",
    "userSetOnLoad": false
  }
}