{
  "gitSyncId": "66878fc8470ac81ae3da028e_5e3156d1-40eb-4f1d-ae19-fe3b300bf377",
  "id": "Engineering Stats_CommonHigh.getAforceCount",
  "pluginId": "js-plugin",
  "pluginType": "JS",
  "unpublishedAction": {
    "actionConfiguration": {
      "encodeParamsToggle": true,
      "jsArguments": [],
      "paginationType": "NONE",
      "timeoutInMillisecond": 10000
    },
    "collectionId": "Engineering Stats_CommonHigh",
    "confirmBeforeExecute": false,
    "datasource": {
      "isAutoGenerated": false,
      "name": "UNUSED_DATASOURCE",
      "pluginId": "js-plugin"
    },
    "dynamicBindingPathList": [
      {
        "key": "body"
      }
    ],
    "fullyQualifiedName": "CommonHigh.getAforceCount",
    "name": "getAforceCount",
    "pageId": "Engineering Stats",
    "runBehaviour": "MANUAL",
    "userSetOnLoad": false
  }
}